aicampxyz/Bert.py
aicampxyz/__init__.py
aicampxyz/setup.py
aicampxyz-0.1.dist-info/METADATA
aicampxyz-0.1.dist-info/WHEEL
aicampxyz-0.1.dist-info/top_level.txt
aicampxyz-0.1.dist-info/RECORD
